MANIFEST.in
board_hr_expense_view.xml
hr.expense.expense.csv
hr_expense_data.xml
hr_expense_demo.xml
hr_expense_installer_view.xml
hr_expense_report.xml
hr_expense_sequence.xml
hr_expense_view.xml
hr_expense_workflow.xml
setup.py
./__init__.py
./__openerp__.py
./hr_expense.py
./report/__init__.py
./report/expense.py
./report/hr_expense_report.py
i18n/ar.po
i18n/bg.po
i18n/bs.po
i18n/ca.po
i18n/cs.po
i18n/da.po
i18n/de.po
i18n/el.po
i18n/es.po
i18n/es_AR.po
i18n/es_CR.po
i18n/es_EC.po
i18n/es_MX.po
i18n/es_VE.po
i18n/et.po
i18n/fi.po
i18n/fr.po
i18n/hr.po
i18n/hr_expense.pot
i18n/hu.po
i18n/id.po
i18n/it.po
i18n/ja.po
i18n/ko.po
i18n/lt.po
i18n/lv.po
i18n/mk.po
i18n/mn.po
i18n/nb.po
i18n/nl.po
i18n/nl_BE.po
i18n/pl.po
i18n/pt.po
i18n/pt_BR.po
i18n/ro.po
i18n/ru.po
i18n/sl.po
i18n/sq.po
i18n/sr.po
i18n/sr@latin.po
i18n/sv.po
i18n/th.po
i18n/tlh.po
i18n/tr.po
i18n/uk.po
i18n/vi.po
i18n/zh_CN.po
i18n/zh_TW.po
images/hr_expenses.jpeg
images/hr_expenses_analysis.jpeg
openerp_hr_expense.egg-info/PKG-INFO
openerp_hr_expense.egg-info/SOURCES.txt
openerp_hr_expense.egg-info/dependency_links.txt
openerp_hr_expense.egg-info/requires.txt
openerp_hr_expense.egg-info/top_level.txt
process/hr_expense_process.xml
report/expense.rml
report/expense.sxw
report/hr_expense_report_view.xml
security/ir.model.access.csv
security/ir_rule.xml
static/src/img/icon.png
test/expense_demo.yml
test/expense_process.yml